topsis/__init__.py
topsis/__main__.py
Topsis_Bhavika_101903538-1.0.0.dist-info/LICENCE
Topsis_Bhavika_101903538-1.0.0.dist-info/METADATA
Topsis_Bhavika_101903538-1.0.0.dist-info/WHEEL
Topsis_Bhavika_101903538-1.0.0.dist-info/entry_points.txt
Topsis_Bhavika_101903538-1.0.0.dist-info/top_level.txt
Topsis_Bhavika_101903538-1.0.0.dist-info/RECORD
