Metadata-Version: 2.1
Name: Topsis-Bhavika-101903538
Version: 1.0.0
Summary: It performs topsis for any model
Home-page: https://github.com/bhavi-0/topsis-bhavika-1019035338.git
Author: Bhavika
Author-email: bhavikaa2301@gmail.com
License: MIT
Platform: UNKNOWN
Classifier: License :: OSI Approved :: MIT License
Classifier: Programming Language :: Python :: 3.6
Classifier: Programming Language :: Python :: 3.7
Classifier: Programming Language :: Python :: 3.8
License-File: LICENCE
